setup.py
bamb.egg-info/PKG-INFO
bamb.egg-info/SOURCES.txt
bamb.egg-info/dependency_links.txt
bamb.egg-info/top_level.txt
common/__init__.py
common/constants.py
common/utils.py
domain/__init__.py
domain/base.py
domain/exceptions.py
domain/forms.py
domain/task.py
domain/user.py
persist/__init__.py
persist/beans.py
persist/simple_repository.py
persist/task_repo.py
persist/utils_repo.py
rest/__init__.py
rest/admin.py
rest/background.py
rest/beans.py
rest/events.py
rest/models.py
rest/tasks.py
rest/tests.py
rest/urls.py
rest/views.py
rest/worker.py
rest/migrations/__init__.py
service/__init__.py
service/_global_variables.py
service/amqp_service.py
service/beans.py
service/beans_service.py
service/built_in_executors.py
service/command_service.py
service/event_service.py
service/repositories.py
service/salt.py
service/simple.py
service/task_service.py
service/user_service.py
service/utils.py
test/__init__.py
test/dependency_injection_test.py
test/exceptions_test.py
test/id_generator_test.py
test/list_tree_test.py
test/mongdb_test.py
test/package_scan_test.py
test/ply_test.py
test/serialization_test.py
test/simple_test1.py
test/target_test.py
test/task_test.py
ui/__init__.py
ui/admin.py
ui/models.py
ui/tests.py
ui/urls.py
ui/views.py
ui/migrations/__init__.py
web/__init__.py
web/my_celery.py
web/settings.py
web/urls.py
web/wsgi.py