Metadata-Version: 1.0
Name: bamb
Version: 0.7.0
Summary: interactive celery
Home-page: http://sharework.cn
Author: sharework
Author-email: sharework@qq.com
License: MIT
Keywords: bamb
Platform: UNKNOWN
